tests/__init__.py
tests/http_response_catcher.py
tests/test_helper.py
tests/controllers/__init__.py
tests/controllers/controller_test_base.py
tests/controllers/test_simple_calculator_controller.py
version_test_v_2/__init__.py
version_test_v_2/api_helper.py
version_test_v_2/configuration.py
version_test_v_2/decorators.py
version_test_v_2/version_test_v_2_client.py
version_test_v_2/controllers/__init__.py
version_test_v_2/controllers/base_controller.py
version_test_v_2/controllers/simple_calculator_controller.py
version_test_v_2/exceptions/__init__.py
version_test_v_2/exceptions/api_exception.py
version_test_v_2/http/__init__.py
version_test_v_2/http/http_call_back.py
version_test_v_2/http/http_client.py
version_test_v_2/http/http_context.py
version_test_v_2/http/http_method_enum.py
version_test_v_2/http/http_request.py
version_test_v_2/http/http_response.py
version_test_v_2/http/requests_client.py
version_test_v_2/models/__init__.py
version_test_v_2/models/operation_type_enum.py
version_test_v2-1.0.0.dist-info/LICENSE
version_test_v2-1.0.0.dist-info/METADATA
version_test_v2-1.0.0.dist-info/WHEEL
version_test_v2-1.0.0.dist-info/top_level.txt
version_test_v2-1.0.0.dist-info/RECORD
